<annotation>
	<folder>maskDetectorJPEGImages</folder>
	<filename>177.jpg</filename>
	<path>maskDetectorJPEGImages/177.jpg</path>
	<source>
		<database>Unknown</database>
	</source>
	<size>
		<width>1920</width>
		<height>1080</height>
		<depth>3</depth>
	</size>
	<segmented>0</segmented>
	<object>
		<name>noMask</name>
		<pose>Unspecified</pose>
		<truncated>0</truncated>
		<difficult>0</difficult>
		<bndbox>
			<xmin>1073</xmin>
			<ymin>16</ymin>
			<xmax>1850</xmax>
			<ymax>1021</ymax>
		</bndbox>
	</object>
</annotation>
