<annotation>
	<folder>maskDetectorJPEGImages</folder>
	<filename>187.jpg</filename>
	<path>maskDetectorJPEGImages/187.jpg</path>
	<source>
		<database>Unknown</database>
	</source>
	<size>
		<width>182</width>
		<height>277</height>
		<depth>3</depth>
	</size>
	<segmented>0</segmented>
	<object>
		<name>noMask</name>
		<pose>Unspecified</pose>
		<truncated>0</truncated>
		<difficult>0</difficult>
		<bndbox>
			<xmin>37</xmin>
			<ymin>18</ymin>
			<xmax>161</xmax>
			<ymax>172</ymax>
		</bndbox>
	</object>
</annotation>
