<annotation>
	<folder>maskDetectorJPEGImages</folder>
	<filename>487.jpg</filename>
	<path>maskDetectorJPEGImages/487.jpg</path>
	<source>
		<database>Unknown</database>
	</source>
	<size>
		<width>1000</width>
		<height>1620</height>
		<depth>3</depth>
	</size>
	<segmented>0</segmented>
	<object>
		<name>mask</name>
		<pose>Unspecified</pose>
		<truncated>0</truncated>
		<difficult>0</difficult>
		<bndbox>
			<xmin>144</xmin>
			<ymin>109</ymin>
			<xmax>928</xmax>
			<ymax>861</ymax>
		</bndbox>
	</object>
</annotation>
