<annotation>
	<folder>maskDetectorJPEGImages</folder>
	<filename>590.jpg</filename>
	<path>maskDetectorJPEGImages/590.jpg</path>
	<source>
		<database>Unknown</database>
	</source>
	<size>
		<width>400</width>
		<height>400</height>
		<depth>3</depth>
	</size>
	<segmented>0</segmented>
	<object>
		<name>mask</name>
		<pose>Unspecified</pose>
		<truncated>0</truncated>
		<difficult>0</difficult>
		<bndbox>
			<xmin>108</xmin>
			<ymin>13</ymin>
			<xmax>323</xmax>
			<ymax>293</ymax>
		</bndbox>
	</object>
</annotation>
